LICENSE
README.md
mtlibrary.py
setup.py
mtlibrary.egg-info/PKG-INFO
mtlibrary.egg-info/SOURCES.txt
mtlibrary.egg-info/dependency_links.txt
mtlibrary.egg-info/top_level.txt