Metadata-Version: 2.1
Name: mtlibrary
Version: 2.0.5
Summary: MTLibrary es una libreria en español desarrollada para resolver problemas matemáticos y así ayudar a esos programadores con bajos conocimientos con librerias en inglés.
Home-page: https://github.com/estuardodev/MTLibrary
Author: Estuardo Ramírez
Author-email: estuardo@estuardodev.com
License: MIT
Download-URL: https://github.com/estuardodev/MTLibrary.git
Keywords: estuardodev,mtlibrary,matematicas,math
Platform: UNKNOWN
Classifier: Programming Language :: Python :: 3.9
Classifier: License :: OSI Approved :: MIT License
Classifier: Operating System :: OS Independent
